a2a_client_handler/__init__.py
a2a_client_handler/services/remote_agent_connection.py
a2a_client_handler/services/routing_agent.py
a2a_client_handler/services/routing_sequential.py
a2a_client_handler-0.1.0.dist-info/METADATA
a2a_client_handler-0.1.0.dist-info/WHEEL
a2a_client_handler-0.1.0.dist-info/entry_points.txt
a2a_client_handler-0.1.0.dist-info/RECORD
