Metadata-Version: 2.4
Name: a2a-client-handler
Version: 0.1.0
Summary: Package used to define A2A clients to enable communication with remote agents.
Requires-Python: >=3.10
Requires-Dist: a2a-sdk>=0.3.0
Requires-Dist: httpx>=0.28.1
Requires-Dist: langchain-community==0.3.19
Requires-Dist: langchain-core==0.3.68
Requires-Dist: langchain-mcp-adapters==0.1.9
Requires-Dist: langchain-openai==0.3.11
Requires-Dist: langchain-tavily==0.2.7
Requires-Dist: langchain-text-splitters==0.3.8
Requires-Dist: langchain==0.3.26
Requires-Dist: langgraph-checkpoint==2.1.0
Requires-Dist: langgraph-prebuilt==0.5.2
Requires-Dist: langgraph-sdk==0.1.72
Requires-Dist: langgraph-supervisor==0.0.27
Requires-Dist: langgraph==0.5.1
Requires-Dist: openai==1.69.0
Requires-Dist: pydantic<3.0.0,>=2.7.0
Requires-Dist: python-dotenv<2.0.0,>=1.0.1
